tt/__init__.py
tt/db.py
tt/main.py
tt/model.py
tt/stmt.py
tt/util.py
tt/test/__init__.py
tt/test/test_db.py
tt/test/test_model.py
tt_focus-0.0.4.dist-info/entry_points.txt
tt_focus-0.0.4.dist-info/LICENSE
tt_focus-0.0.4.dist-info/WHEEL
tt_focus-0.0.4.dist-info/METADATA
tt_focus-0.0.4.dist-info/RECORD
